pytrodactyl/__init__.py
pytrodactyl-0.0.2.dist-info/LICENSE.txt
pytrodactyl-0.0.2.dist-info/METADATA
pytrodactyl-0.0.2.dist-info/WHEEL
pytrodactyl-0.0.2.dist-info/top_level.txt
pytrodactyl-0.0.2.dist-info/RECORD
