Metadata-Version: 2.1
Name: pytrodactyl
Version: 0.0.2
Summary: An API Wrapper for the Pterodactyl Panel.
Home-page: https://github.com/INfoUpgraders/pytrodactyl
Author: INfoUpgraders
License: MIT
Project-URL: Documentation, https://pytrodactyl.readthedocs.io/en/latest/
Project-URL: Issue tracker, https://github.com/INfoUpgraders/pytrodactyl/issues
Platform: UNKNOWN
Classifier: Development Status :: 5 - Production/Stable
Classifier: License :: OSI Approved :: MIT License
Classifier: Intended Audience :: Developers
Classifier: Natural Language :: English
Classifier: Operating System :: OS Independent
Classifier: Programming Language :: Python :: 3.6
Classifier: Programming Language :: Python :: 3.7
Classifier: Programming Language :: Python :: 3.8
Classifier: Topic :: Internet
Classifier: Topic :: Software Development :: Libraries
Classifier: Topic :: Software Development :: Libraries :: Python Modules
Classifier: Topic :: Utilities
Requires-Python: >=3.6
Requires-Dist: requests (>=2.20.0)
Provides-Extra: docs
Requires-Dist: sphinx (==1.8.5) ; extra == 'docs'
Requires-Dist: sphinxcontrib-trio (==1.1.1) ; extra == 'docs'
Requires-Dist: sphinxcontrib-websupport ; extra == 'docs'
